{
  "info": {
    "name": "webflux-reativo API",
    "_postman_id": "b8f3a4d2-0000-4000-8000-000000000000",
    "description": "Coleção para testar os endpoints de /users da aplicação webflux-reativo. Base URL: {{baseUrl}}",
    "schema": "https://schema.getpostman.com/json/collection/v2.1.0/collection.json"
  },
  "variable": [
    {
      "key": "baseUrl",
      "value": "http://localhost:8091",
      "type": "string"
    },
    {
      "key": "userId",
      "value": "REPLACE_ID",
      "type": "string"
    }
  ],
  "item": [
    {
      "name": "List Users",
      "request": {
        "method": "GET",
        "header": [
          {
            "key": "Accept",
            "value": "application/json"
          }
        ],
        "url": {
          "raw": "{{baseUrl}}/users",
          "host": ["{{baseUrl}}"],
          "path": ["users"]
        }
      },
      "response": []
    },
    {
      "name": "Get User by ID",
      "request": {
        "method": "GET",
        "header": [
          {
            "key": "Accept",
            "value": "application/json"
          }
        ],
        "url": {
          "raw": "{{baseUrl}}/users/{{userId}}",
          "host": ["{{baseUrl}}"],
          "path": ["users","{{userId}}"]
        }
      },
      "response": []
    },
    {
      "name": "Create User",
      "request": {
        "method": "POST",
        "header": [
          {
            "key": "Content-Type",
            "value": "application/json"
          }
        ],
        "body": {
          "mode": "raw",
          "raw": "{\n  \"name\": \"Joao da Silva\",\n  \"email\": \"joao@example.com\",\n  \"password\": \"senhaSegura123\"\n}",
          "options": {
            "raw": {
              "language": "json"
            }
          }
        },
        "url": {
          "raw": "{{baseUrl}}/users",
          "host": ["{{baseUrl}}"],
          "path": ["users"]
        }
      },
      "response": []
    },
    {
      "name": "Update User",
      "request": {
        "method": "PUT",
        "header": [
          {
            "key": "Content-Type",
            "value": "application/json"
          }
        ],
        "body": {
          "mode": "raw",
          "raw": "{\n  \"name\": \"Joao Atualizado\",\n  \"email\": \"joao.novo@example.com\",\n  \"password\": \"novaSenha456\"\n}",
          "options": {
            "raw": {
              "language": "json"
            }
          }
        },
        "url": {
          "raw": "{{baseUrl}}/users/{{userId}}",
          "host": ["{{baseUrl}}"],
          "path": ["users","{{userId}}"]
        }
      },
      "response": []
    },
    {
      "name": "Delete User",
      "request": {
        "method": "DELETE",
        "header": [],
        "url": {
          "raw": "{{baseUrl}}/users/{{userId}}",
          "host": ["{{baseUrl}}"],
          "path": ["users","{{userId}}"]
        }
      },
      "response": []
    }
  ]
}

